pyramid_captcha/__init__.py
pyramid_captcha/exception.py
pyramid_captcha-1.0.0.dist-info/LICENSE
pyramid_captcha-1.0.0.dist-info/METADATA
pyramid_captcha-1.0.0.dist-info/WHEEL
pyramid_captcha-1.0.0.dist-info/top_level.txt
pyramid_captcha-1.0.0.dist-info/RECORD
