Metadata-Version: 2.1
Name: pyramid-captcha
Version: 1.0.0
Summary: Pyramid Captcha
Home-page: https://gitlab.com/geo-bl-ch/pyramid-captcha
Author: Karsten Deininger
Author-email: karsten.deininger@bl.ch
License: UNKNOWN
Keywords: web pyramid captcha
Platform: UNKNOWN
Classifier: License :: OSI Approved :: BSD License
Classifier: Development Status :: 5 - Production/Stable
Classifier: Programming Language :: Python :: 2.7
Classifier: Programming Language :: Python :: 3.5
Classifier: Programming Language :: Python :: 3.6
Classifier: Programming Language :: Python :: 3.7
Classifier: Programming Language :: Python :: 3.8
Classifier: Framework :: Pyramid
Classifier: Topic :: Internet :: WWW/HTTP
Requires-Dist: captcha
Requires-Dist: pyramid
